epc/__init__.py
epc/encoding/__init__.py
epc/encoding/integer.py
epc/encoding/partition.py
epc/encoding/string.py
epc/encoding/string_partition_table.py
epc/schemes/GIAI.py
epc/schemes/GID.py
epc/schemes/GRAI.py
epc/schemes/SGLN.py
epc/schemes/SGTIN.py
epc/schemes/__init__.py
epc/schemes/base.py
epc/utils/__init__.py
epc/utils/barcode.py
epc/utils/upc.py
epc_encoding_utils-1.3.dist-info/LICENSE.md
epc_encoding_utils-1.3.dist-info/METADATA
epc_encoding_utils-1.3.dist-info/WHEEL
epc_encoding_utils-1.3.dist-info/top_level.txt
epc_encoding_utils-1.3.dist-info/RECORD
