Metadata-Version: 2.1
Name: epc-encoding-utils
Version: 1.3
Summary: Library for encoding/decoding and representing GS1 Electronic Product Codes
Home-page: https://github.com/AACEngineering/epcpy-tools
Author: AAC Engineering
License: MIT
Keywords: epc,rfid,gid,giai,gid,grai,sgln,sgtin,encoding,decoding,barcodes
Platform: UNKNOWN
Classifier: Development Status :: 5 - Production/Stable
Classifier: Intended Audience :: Developers
Classifier: License :: OSI Approved :: Apache Software License
Classifier: Operating System :: OS Independent
Classifier: Programming Language :: Python :: 3
Classifier: Programming Language :: Python :: 3.5
Classifier: Programming Language :: Python :: 3.6
Classifier: Programming Language :: Python :: 3.7
Classifier: Programming Language :: Python :: 3.8
Classifier: Programming Language :: Python :: 3.9
Requires-Python: >=3.5
Requires-Dist: setuptools
